odoo/addons/l10n_be_mis_reports/README.rst
odoo/addons/l10n_be_mis_reports/__init__.py
odoo/addons/l10n_be_mis_reports/__manifest__.py
odoo/addons/l10n_be_mis_reports/data/mis_report_bs.xml
odoo/addons/l10n_be_mis_reports/data/mis_report_pl.xml
odoo/addons/l10n_be_mis_reports/data/mis_report_styles.xml
odoo/addons/l10n_be_mis_reports/data/mis_report_vat.xml
odoo/addons/l10n_be_mis_reports/i18n/fr.po
odoo/addons/l10n_be_mis_reports/i18n/l10n_be_mis_reports.pot
odoo/addons/l10n_be_mis_reports/i18n/nl.po
odoo/addons/l10n_be_mis_reports/static/description/icon.png
odoo11_addon_l10n_be_mis_reports-11.0.1.1.2.dist-info/METADATA
odoo11_addon_l10n_be_mis_reports-11.0.1.1.2.dist-info/WHEEL
odoo11_addon_l10n_be_mis_reports-11.0.1.1.2.dist-info/top_level.txt
odoo11_addon_l10n_be_mis_reports-11.0.1.1.2.dist-info/RECORD
